{
  "blackbeard:WeaponPower": {
    "NAME": "Weapons",
    "DESCRIPTIONS": [
      "Whenever you play an attack card, one Durability of your rightmost Weapon is used and card's damage is increased by Weapon's Attack. You can equip maximum of #b10 Weapons."
    ]
  },
  "blackbeard:ParrotPower": {
    "NAME": "Parrot",
    "DESCRIPTIONS": [
      "The last card played each turn is played an additional time."
    ]
  },
  "blackbeard:TheDrunkenSailorPower": {
    "NAME": "The Drunken Sailor",
    "DESCRIPTIONS": [
      "Whenever you use a potion, use it #b",
      " times."
    ]
  },
  "blackbeard:SwordDancePower": {
    "NAME": "Sword Dance",
    "DESCRIPTIONS": [
      "This turn, your next Attack uses all equipped Weapons.",
      "This turn, your next #b",
      " Attacks use all equipped Weapons."
    ]
  },
  "blackbeard:ResistancePower": {
    "NAME": "Resistance",
    "DESCRIPTIONS": [
      "You take #b",
      " less",
      " more",
      " damage from enemy attacks. (Enemy intents always show actual incoming damage, with Resistance taken into account.)"
    ]
  },
  "blackbeard:InfiniteBarragePower": {
    "NAME": "Infinite Barrage",
    "DESCRIPTIONS": [
      "At the start of your turn, add #b",
      " #yCannonball",
      " #yCannonballs",
      " into your hand."
    ]
  },
  "blackbeard:ToastPower": {
    "NAME": "Toast",
    "DESCRIPTIONS": [
      "At the start of your next turn, lose #b",
      " #yResistance."
    ]
  },
  "blackbeard:DamageAtTheEndOfNextTurnPower": {
    "NAME": "End Of Next Turn Damage",
    "DESCRIPTIONS": [
      "At the end of next turn, you take #b",
      " damage."
    ]
  },
  "blackbeard:DamageAtTheEndOfThisTurnPower": {
    "NAME": "End Turn Damage",
    "DESCRIPTIONS": [
      "At the end of this turn, you take #b",
      " damage."
    ]
  },
  "blackbeard:WeaponMasteryPower": {
    "NAME": "Weapon Mastery",
    "DESCRIPTIONS": [
      "Whenever you equip a #yWeapon, draw #b",
      " card.",
      " cards."
    ]
  },
  "blackbeard:SalvagerPower": {
    "NAME": "Salvager",
    "DESCRIPTIONS": [
      "Whenever a #yWeapon is destroyed, gain #b",
      " [E] ."
    ]
  },
  "blackbeard:LoseEnergyNextTurnPower": {
    "NAME": "Lose Energy Next Turn",
    "DESCRIPTIONS": [
      "At the start of your next turn, lose #b",
      " [E] ."
    ]
  },
  "blackbeard:ArmorUpPower": {
    "NAME": "Armor Up",
    "DESCRIPTIONS": [
      "This turn, whenever you attack with a #yWeapon, gain #b",
      " #yBlock."
    ]
  },
  "blackbeard:IntoxicationPower": {
    "NAME": "Intoxication",
    "DESCRIPTIONS": [
      "At the start of your turn, lose #b",
      " #yResistance."
    ]
  },
  "blackbeard:PenknifePower": {
    "NAME": "Penknife",
    "DESCRIPTIONS": [
      "Your next #yAttack that uses at least one #yWeapon deals double damage."
    ]
  },
  "blackbeard:DamageWhenIntangibleEndsPower": {
    "NAME": "End Of Intangible Damage",
    "DESCRIPTIONS": [
      "At the start of the turn on which you are no longer #yIntangible, you take #b",
      " damage."
    ]
  },
  "blackbeard:RustyThorns": {
    "NAME": "Rusty Thorns",
    "DESCRIPTIONS": [
      "When attacked, deals #b ",
      " damage back and reduces Rusty Thorns by #b1."
    ]
  },
  "blackbeard:WeaponProficiencyPower": {
    "NAME": "Weapon Proficiency",
    "DESCRIPTIONS": [
      "Your attacks use #b",
      " additional #yWeapon.",
      " additional #yWeapons."
    ]
  },
  "blackbeard:GoldToLootPower": {
    "NAME": "Gold to Loot",
    "DESCRIPTIONS": [
      "Whenever you hit an enemy, gain #b",
      " #yGold. You can gain #b",
      " #yGold more."
    ]
  },
  "blackbeard:BleedPower": {
    "NAME": "Bleed",
    "DESCRIPTIONS": [
      "At the start of its turn, loses #b",
      " HP."
    ]
  },
  "blackbeard:ReapersMarkPower": {
    "NAME": "Reaper's Mark",
    "DESCRIPTIONS": [
      "For every #b3 stacks, creature loses HP equal to #b40% of its missing HP."
    ]
  },
  "blackbeard:ProvisioningPower": {
    "NAME": "Provisioning",
    "DESCRIPTIONS": [
      "Next turn, obtain #b",
      " random potion",
      " random potions",
      "."
    ]
  }
}
